copycat/__init__.py
copycat/__main__.py
copycat/models/__init__.py
copycat/models/custom_base_model.py
copycat/models/history/__init__.py
copycat/models/history/history.py
copycat/models/history/history_status.py
copycat/models/log_level.py
copycat/models/move/__init__.py
copycat/models/move/move.py
copycat/models/move/move_type.py
copycat/run.py
copycat/services/__init__.py
copycat/services/listeners_service.py
copycat/services/playback_service.py
copycat/services/storage_service.py
copycat/shared/__init__.py
copycat/shared/exceptions/general_exception.py
copycat/shared/utils/__init__.py
copycat/shared/utils/generic.py
copycat/shared/utils/logger.py
copycat/tool/__init__.py
copycat/tool/tool.py
copycat-0.1.3.dist-info/LICENSE
copycat-0.1.3.dist-info/METADATA
copycat-0.1.3.dist-info/WHEEL
copycat-0.1.3.dist-info/entry_points.txt
copycat-0.1.3.dist-info/RECORD
