Metadata-Version: 2.1
Name: copycat
Version: 0.1.3
Summary: A tool that record and replay keyboard and mouse macro.
Home-page: https://github.com/ZappaBoy/copycat
Keywords: copycat,productivity,macro,keyboard,mouse
Author: ZappaBoy
Author-email: federico.zappone@justanother.cloud
Maintainer: ZappaBoy
Maintainer-email: federico.zappone@justanother.cloud
Requires-Python: >=3.11,<3.14
Classifier: Programming Language :: Python :: 3
Classifier: Programming Language :: Python :: 3.11
Classifier: Programming Language :: Python :: 3.12
Classifier: Topic :: Utilities
Requires-Dist: joblib (>=1.4.2,<2.0.0)
Requires-Dist: pyautogui (>=0.9.54,<0.10.0)
Requires-Dist: pydantic (>=2.4.2,<3.0.0)
Requires-Dist: pynput (>=1.7.7,<2.0.0)
Requires-Dist: ttkthemes (>=3.2.2,<4.0.0)
Project-URL: Documentation, https://github.com/ZappaBoy/copycat/blob/main/README.md
Project-URL: Repository, https://github.com/ZappaBoy/copycat
